mindflow/__init__.py
mindflow/setup.py
mindflow/cell/__init__.py
mindflow/cell/activation.py
mindflow/cell/basic_block.py
mindflow/cell/unet2d.py
mindflow/cell/utils.py
mindflow/cell/neural_operators/__init__.py
mindflow/cell/neural_operators/dft.py
mindflow/cell/neural_operators/fno.py
mindflow/cell/neural_operators/kno1d.py
mindflow/cell/neural_operators/kno2d.py
mindflow/cell/neural_operators/m2k.py
mindflow/cell/neural_operators/pdenet.py
mindflow/cell/neural_operators/percnn.py
mindflow/cell/transformer/__init__.py
mindflow/cell/transformer/layer.py
mindflow/cell/transformer/vit.py
mindflow/cfd/__init__.py
mindflow/cfd/mesh_info.py
mindflow/cfd/runtime.py
mindflow/cfd/simulator.py
mindflow/cfd/utils.py
mindflow/cfd/visualization.py
mindflow/cfd/boundary_conditions/__init__.py
mindflow/cfd/boundary_conditions/base.py
mindflow/cfd/boundary_conditions/boundary_manager.py
mindflow/cfd/boundary_conditions/neumann.py
mindflow/cfd/boundary_conditions/periodic.py
mindflow/cfd/boundary_conditions/symmetry.py
mindflow/cfd/boundary_conditions/wall.py
mindflow/cfd/integrator/__init__.py
mindflow/cfd/integrator/base.py
mindflow/cfd/integrator/euler.py
mindflow/cfd/integrator/runge_kutta3.py
mindflow/cfd/material/__init__.py
mindflow/cfd/material/base.py
mindflow/cfd/material/ideal_gas.py
mindflow/cfd/space_solver/__init__.py
mindflow/cfd/space_solver/godunov_flux.py
mindflow/cfd/space_solver/space_solver.py
mindflow/cfd/space_solver/viscous_flux.py
mindflow/cfd/space_solver/derivative_computer/__init__.py
mindflow/cfd/space_solver/derivative_computer/base.py
mindflow/cfd/space_solver/derivative_computer/forth_order_central_derivative_computer.py
mindflow/cfd/space_solver/derivative_computer/forth_order_face_derivative_computer.py
mindflow/cfd/space_solver/interpolator/__init__.py
mindflow/cfd/space_solver/interpolator/base.py
mindflow/cfd/space_solver/interpolator/central_forth_order_interpolator.py
mindflow/cfd/space_solver/reconstructor/__init__.py
mindflow_gpu-0.2.0.dist-info/METADATA
mindflow_gpu-0.2.0.dist-info/WHEEL
mindflow_gpu-0.2.0.dist-info/top_level.txt
mindflow_gpu-0.2.0.dist-info/RECORD
